CMakeLists.txt
LICENSE
README.md
pyproject.toml
setup.cfg
setup.py
swig_lib.cmake
doc/OpenDB-AddFieldsInDbObjects.md
include/odb/ISdb.h
include/odb/IZdcr.h
include/odb/ZComponents.h
include/odb/ZException.h
include/odb/ZFactory.h
include/odb/ZInterface.h
include/odb/ZObject.h
include/odb/array1.h
include/odb/array2d.h
include/odb/box.h
include/odb/cdl.h
include/odb/darr.h
include/odb/db.h
include/odb/dbBlockCallBackObj.h
include/odb/dbBlockSet.h
include/odb/dbCCSegSet.h
include/odb/dbDiff.h
include/odb/dbExtControl.h
include/odb/dbId.h
include/odb/dbIterator.h
include/odb/dbMap.h
include/odb/dbMap.hpp
include/odb/dbMatrix.h
include/odb/dbNetSet.h
include/odb/dbObject.h
include/odb/dbRtEdge.h
include/odb/dbRtNode.h
include/odb/dbRtTree.h
include/odb/dbSearch.h
include/odb/dbSet.h
include/odb/dbShape.h
include/odb/dbStream.h
include/odb/dbTransform.h
include/odb/dbTypes.h
include/odb/dbUtil.h
include/odb/dbViaParams.h
include/odb/dbWireCodec.h
include/odb/dbWireGraph.h
include/odb/defin.h
include/odb/defout.h
include/odb/geom.h
include/odb/gseq.h
include/odb/isotropy.h
include/odb/lefin.h
include/odb/lefout.h
include/odb/misc_global.h
include/odb/name.h
include/odb/odb.h
include/odb/odbAllocator.h
include/odb/odbDList.h
include/odb/parse.h
include/odb/poly_decomp.h
include/odb/rcx.h
include/odb/util.h
include/odb/version.hh.in
include/odb/wOrder.h
include/odb/wire.h
include/utl/Logger.h
src/OpenROAD_OpenDbPy.egg-info/PKG-INFO
src/OpenROAD_OpenDbPy.egg-info/SOURCES.txt
src/OpenROAD_OpenDbPy.egg-info/dependency_links.txt
src/OpenROAD_OpenDbPy.egg-info/not-zip-safe
src/OpenROAD_OpenDbPy.egg-info/requires.txt
src/OpenROAD_OpenDbPy.egg-info/top_level.txt
src/cdl/CMakeLists.txt
src/cdl/cdl.cpp
src/codeGenerator/README.md
src/codeGenerator/dbAccessPoint.json
src/codeGenerator/dbGCellGrid.json
src/codeGenerator/dbGlobalConnect.json
src/codeGenerator/dbGroup.json
src/codeGenerator/dbGuide.json
src/codeGenerator/dbMetalWidthViaMap.json
src/codeGenerator/dbTechLayer.json
src/codeGenerator/dbTechLayerAreaRule.json
src/codeGenerator/dbTechLayerArraySpacingRule.json
src/codeGenerator/dbTechLayerCornerSpacingRule.json
src/codeGenerator/dbTechLayerCutClassRule.json
src/codeGenerator/dbTechLayerCutEnclosureRule.json
