Metadata-Version: 2.1
Name: OpenROAD-OpenDbPy
Version: 0.0.0
Summary: OpenDb fromo OpenROAD project
Home-page: https://github.com/jonpry/OpenDb
Author: Jon Pry
Author-email: jonpry@gmail.com
License: MIT
Project-URL: Source, https://github.com/jonpry/OpenDb/tree/master/
Project-URL: Tracker, https://github.com/jonpry/OpenDb/issues
Keywords: setuptools extension cpp cmake build package pypi bindings swig pybind11
Platform: any
Requires-Python: >=3.6
Provides-Extra: all
Provides-Extra: test
